stp_scraper/__init__.py
stp_scraper/client.py
stp_scraper/exceptions.py
stp_scraper-0.1.8.dist-info/LICENSE
stp_scraper-0.1.8.dist-info/METADATA
stp_scraper-0.1.8.dist-info/WHEEL
stp_scraper-0.1.8.dist-info/top_level.txt
stp_scraper-0.1.8.dist-info/RECORD
