Metadata-Version: 2.1
Name: stp-scraper
Version: 0.1.8
Summary: Extract sent and received transactions of an STP account.
Home-page: https://github.com/cuenca-mx/stp-scraper
Author: Cuenca
Author-email: dev@cuenca.com
License: UNKNOWN
Platform: UNKNOWN
Classifier: Programming Language :: Python :: 3
Classifier: License :: OSI Approved :: MIT License
Classifier: Operating System :: OS Independent
Requires-Dist: requests (<2.22.0,>=2.21.0)
Requires-Dist: SQLAlchemy (<1.3,>=1.2.18)
Requires-Dist: sqlalchemy-redshift (<0.8,>=0.7.3)
Requires-Dist: bs4 (<0.0.2,>=0.0.1)
Provides-Extra: test
Requires-Dist: pytest ; extra == 'test'
Requires-Dist: pytest-vcr ; extra == 'test'
Requires-Dist: pycodestyle ; extra == 'test'
Requires-Dist: pytest-cov ; extra == 'test'
Requires-Dist: black ; extra == 'test'
Requires-Dist: isort ; extra == 'test'
Requires-Dist: moto ; extra == 'test'
Requires-Dist: flake8 ; extra == 'test'
Requires-Dist: responses ; extra == 'test'
Requires-Dist: google-compute-engine ; extra == 'test'
